mlon/__init__.py
mlon/auto_check.py
mlon/cli.py
mlon/cross_validation.py
mlon/exceptions.py
mlon/feature_selection.py
mlon/guardrails.py
mlon/logging.py
mlon/metrics.py
mlon/model_utils.py
mlon/preprocessing.py
mlon/time_series.py
mlon/visualization.py
mlon-1.2.1.dist-info/licenses/LICENSE
mlon-1.2.1.dist-info/METADATA
mlon-1.2.1.dist-info/WHEEL
mlon-1.2.1.dist-info/entry_points.txt
mlon-1.2.1.dist-info/top_level.txt
mlon-1.2.1.dist-info/RECORD
