Metadata-Version: 2.4
Name: mlon
Version: 1.2.1
Summary: A comprehensive utility package for machine learning development
Home-page: https://github.com/chasegalloway/mlon
Author: Chase Galloway
Author-email: chase.h.galloway21@gmail.com
Project-URL: Bug Tracker, https://github.com/chasegalloway/mlon/issues
Project-URL: Documentation, https://github.com/chasegalloway/mlon#readme
Project-URL: Source Code, https://github.com/chasegalloway/mlon
Classifier: Development Status :: 5 - Production/Stable
Classifier: Intended Audience :: Developers
Classifier: Intended Audience :: Science/Research
Classifier: Programming Language :: Python :: 3
Classifier: Programming Language :: Python :: 3.7
Classifier: Programming Language :: Python :: 3.8
Classifier: Programming Language :: Python :: 3.9
Classifier: Topic :: Scientific/Engineering :: Artificial Intelligence
Classifier: License :: OSI Approved :: MIT License
Classifier: Operating System :: OS Independent
Requires-Python: >=3.7
License-File: LICENSE
Requires-Dist: numpy>=1.19.0
Requires-Dist: pandas>=1.1.0
Requires-Dist: scikit-learn>=0.24.0
Requires-Dist: matplotlib>=3.3.0
Requires-Dist: seaborn>=0.11.0
Requires-Dist: joblib>=1.0.0
Requires-Dist: scipy>=1.6.0
Requires-Dist: click>=8.0.0
Requires-Dist: reportlab>=3.6.0
Dynamic: author
Dynamic: author-email
Dynamic: classifier
Dynamic: description
Dynamic: description-content-type
Dynamic: home-page
Dynamic: license-file
Dynamic: project-url
Dynamic: requires-dist
Dynamic: requires-python
Dynamic: summary
